{
  "account": {
    "cash": "-19083.58",
    "equity": "17268.71",
    "portfolioValue": "17268.71",
    "originalInvestment": 20000
  },
  "history": [
    {
      "timestamp": 1766451600,
      "equity": 20034.39,
      "change": -102.76,
      "changePercent": -0.0051
    },
    {
      "timestamp": 1766538000,
      "equity": 20281.71,
      "change": 247.32,
      "changePercent": 0.0123
    },
    {
      "timestamp": 1766613600,
      "equity": 20335.31,
      "change": 53.6,
      "changePercent": 0.0026
    },
    {
      "timestamp": 1766797200,
      "equity": 20480.1,
      "change": 144.79,
      "changePercent": 0.0071
    },
    {
      "timestamp": 1767056400,
      "equity": 18758.41,
      "change": -1721.69,
      "changePercent": -0.0841
    },
    {
      "timestamp": 1767142800,
      "equity": 19059.08,
      "change": 300.67,
      "changePercent": 0.016
    },
    {
      "timestamp": 1767229200,
      "equity": 18568.07,
      "change": -491.01,
      "changePercent": -0.0258
    },
    {
      "timestamp": 1767402000,
      "equity": 19729.36,
      "change": 1161.29,
      "changePercent": 0.0625
    },
    {
      "timestamp": 1767661200,
      "equity": 21052.29,
      "change": 1322.93,
      "changePercent": 0.0671
    },
    {
      "timestamp": 1767747600,
      "equity": 22485.77,
      "change": 1433.48,
      "changePercent": 0.0681
    },
    {
      "timestamp": 1767834000,
      "equity": 21931.53,
      "change": -554.24,
      "changePercent": -0.0246
    },
    {
      "timestamp": 1767920400,
      "equity": 18819.02,
      "change": -3112.51,
      "changePercent": -0.1419
    },
    {
      "timestamp": 1768006800,
      "equity": 19172.46,
      "change": 353.44,
      "changePercent": 0.0188
    },
    {
      "timestamp": 1768266000,
      "equity": 21843.66,
      "change": 2671.2,
      "changePercent": 0.1393
    },
    {
      "timestamp": 1768352400,
      "equity": 21638.52,
      "change": -205.14,
      "changePercent": -0.0094
    },
    {
      "timestamp": 1768438800,
      "equity": 22606.79,
      "change": 968.27,
      "changePercent": 0.0447
    },
    {
      "timestamp": 1768525200,
      "equity": 19802.46,
      "change": -2804.33,
      "changePercent": -0.124
    },
    {
      "timestamp": 1768611600,
      "equity": 17319.17,
      "change": -2483.29,
      "changePercent": -0.1254
    },
    {
      "timestamp": 1768957200,
      "equity": 18228.99,
      "change": 909.82,
      "changePercent": 0.0525
    },
    {
      "timestamp": 1769043600,
      "equity": 17261.86,
      "change": -967.13,
      "changePercent": -0.0531
    }
  ],
  "positions": [
    {
      "symbol": "AMC",
      "qty": "2",
      "marketValue": "2.8",
      "costBasis": "3.433",
      "currentPrice": "1.4",
      "lastdayPrice": "1.38",
      "changeToday": "0.01449"
    },
    {
      "symbol": "AMZN",
      "qty": "10",
      "marketValue": "2378.4",
      "costBasis": "2279.235",
      "currentPrice": "237.84",
      "lastdayPrice": "238.62",
      "changeToday": "-0.00327"
    },
    {
      "symbol": "GOOGL",
      "qty": "5",
      "marketValue": "1711.25",
      "costBasis": "1543.775",
      "currentPrice": "342.25",
      "lastdayPrice": "339.71",
      "changeToday": "0.00748"
    },
    {
      "symbol": "MSFT",
      "qty": "10",
      "marketValue": "4134.75",
      "costBasis": "4860.035",
      "currentPrice": "413.475",
      "lastdayPrice": "411.21",
      "changeToday": "0.00551"
    },
    {
      "symbol": "NVDA",
      "qty": "33",
      "marketValue": "5911.29",
      "costBasis": "6060.8637",
      "currentPrice": "179.13",
      "lastdayPrice": "180.34",
      "changeToday": "-0.00671"
    },
    {
      "symbol": "QQQ",
      "qty": "10",
      "marketValue": "6139.1",
      "costBasis": "6192.799",
      "currentPrice": "613.91",
      "lastdayPrice": "616.52",
      "changeToday": "-0.00423"
    },
    {
      "symbol": "SGML",
      "qty": "1250",
      "marketValue": "16075",
      "costBasis": "17895.305",
      "currentPrice": "12.86",
      "lastdayPrice": "12.02",
      "changeToday": "0.06988"
    }
  ],
  "activities": {}
}